[
  {
    "Line":"Blue",
    "Stop":"Airport",
    "x":42.374262,
    "y":-71.030395
  },
  {
    "Line":"Blue",
    "Stop":"Aquarium",
    "x":42.359784,
    "y":-71.051652
  },
  {
    "Line":"Blue",
    "Stop":"Beachmont",
    "x":42.39754234,
    "y":-70.99231944
  },
  {
    "Line":"Blue",
    "Stop":"Bowdoin",
    "x":42.361365,
    "y":-71.062037
  },
  {
    "Line":"Blue",
    "Stop":"Government Center",
    "x":42.359705,
    "y":-71.05921499999999
  },
  {
    "Line":"Blue",
    "Stop":"Maverick",
    "x":42.36911856,
    "y":-71.03952958000001
  },
  {
    "Line":"Blue",
    "Stop":"Orient Heights",
    "x":42.386867,
    "y":-71.00473599999999
  },
  {
    "Line":"Blue",
    "Stop":"Revere Beach",
    "x":42.40784254,
    "y":-70.99253321
  },
  {
    "Line":"Blue",
    "Stop":"State Street",
    "x":42.358978,
    "y":-71.057598
  },
  {
    "Line":"Blue",
    "Stop":"Suffolk Downs",
    "x":42.39050067,
    "y":-70.99712259
  },
  {
    "Line":"Blue",
    "Stop":"Wonderland",
    "x":42.41342,
    "y":-70.991648
  },
  {
    "Line":"Blue",
    "Stop":"Wood Island",
    "x":42.3796403,
    "y":-71.02286539000001
  },
  {
    "Line":"Orange",
    "Stop":"Back Bay",
    "x":42.34735,
    "y":-71.075727
  },
  {
    "Line":"Orange",
    "Stop":"Chinatown",
    "x":42.352547,
    "y":-71.062752
  },
  {
    "Line":"Orange",
    "Stop":"Community College",
    "x":42.373622,
    "y":-71.06953300000001
  },
  {
    "Line":"Orange",
    "Stop":"Downtown Crossing",
    "x":42.355518,
    "y":-71.060225
  },
  {
    "Line":"Orange",
    "Stop":"Forest Hills",
    "x":42.300523,
    "y":-71.113686
  },
  {
    "Line":"Orange",
    "Stop":"Green Street",
    "x":42.310525,
    "y":-71.10741400000001
  },
  {
    "Line":"Orange",
    "Stop":"Haymarket",
    "x":42.363021,
    "y":-71.05829
  },
  {
    "Line":"Orange",
    "Stop":"Jackson Square",
    "x":42.323132,
    "y":-71.099592
  },
  {
    "Line":"Orange",
    "Stop":"Malden Center",
    "x":42.426632,
    "y":-71.07411
  },
  {
    "Line":"Orange",
    "Stop":"Mass Ave",
    "x":42.341512,
    "y":-71.083423
  },
  {
    "Line":"Orange",
    "Stop":"North Station",
    "x":42.365577,
    "y":-71.06129
  },
  {
    "Line":"Orange",
    "Stop":"Oak Grove",
    "x":42.43668,
    "y":-71.07109699999999
  },
  {
    "Line":"Orange",
    "Stop":"Roxbury Crossing",
    "x":42.331397,
    "y":-71.095451
  },
  {
    "Line":"Orange",
    "Stop":"Ruggles",
    "x":42.336377,
    "y":-71.088961
  },
  {
    "Line":"Orange",
    "Stop":"State Street",
    "x":42.358978,
    "y":-71.057598
  },
  {
    "Line":"Orange",
    "Stop":"Stony Brook",
    "x":42.317062,
    "y":-71.104248
  },
  {
    "Line":"Orange",
    "Stop":"Sullivan",
    "x":42.383975,
    "y":-71.076994
  },
  {
    "Line":"Orange",
    "Stop":"Tufts Medical",
    "x":42.349662,
    "y":-71.063917
  },
  {
    "Line":"Orange",
    "Stop":"Wellington",
    "x":42.40237,
    "y":-71.077082
  },
  {
    "Line":"Red",
    "Stop":"Alewife",
    "x":42.395428,
    "y":-71.142483
  },
  {
    "Line":"Red",
    "Stop":"Andrew",
    "x":42.330154,
    "y":-71.057655
  },
  {
    "Line":"Red",
    "Stop":"Ashmont",
    "x":42.284652,
    "y":-71.06448899999999
  },
  {
    "Line":"Red",
    "Stop":"Braintree",
    "x":42.2078543,
    "y":-71.0011385
  },
  {
    "Line":"Red",
    "Stop":"Broadway",
    "x":42.342622,
    "y":-71.056967
  },
  {
    "Line":"Red",
    "Stop":"Central Square",
    "x":42.365486,
    "y":-71.103802
  },
  {
    "Line":"Red",
    "Stop":"Charles/MGH",
    "x":42.361166,
    "y":-71.070628
  },
  {
    "Line":"Red",
    "Stop":"Davis",
    "x":42.39674,
    "y":-71.121815
  },
  {
    "Line":"Red",
    "Stop":"Downtown Crossing",
    "x":42.355518,
    "y":-71.060225
  },
  {
    "Line":"Red",
    "Stop":"Fields Corner",
    "x":42.300093,
    "y":-71.061667
  },
  {
    "Line":"Red",
    "Stop":"Harvard Square",
    "x":42.373362,
    "y":-71.118956
  },
  {
    "Line":"Red",
    "Stop":"JFK/UMass",
    "x":42.320685,
    "y":-71.052391
  },
  {
    "Line":"Red",
    "Stop":"Kendall/MIT",
    "x":42.36249079,
    "y":-71.08617653
  },
  {
    "Line":"Red",
    "Stop":"North Quincy",
    "x":42.275275,
    "y":-71.029583
  },
  {
    "Line":"Red",
    "Stop":"Park Street",
    "x":42.35639457,
    "y":-71.0624242
  },
  {
    "Line":"Red",
    "Stop":"Porter Square",
    "x":42.3884,
    "y":-71.11914899999999
  },
  {
    "Line":"Red",
    "Stop":"Quincy Adams",
    "x":42.233391,
    "y":-71.007153
  },
  {
    "Line":"Red",
    "Stop":"Quincy Center",
    "x":42.251809,
    "y":-71.005409
  },
  {
    "Line":"Red",
    "Stop":"Savin Hill",
    "x":42.31129,
    "y":-71.053331
  },
  {
    "Line":"Red",
    "Stop":"Shawmut",
    "x":42.29312583,
    "y":-71.06573796000001
  },
  {
    "Line":"Red",
    "Stop":"South Station",
    "x":42.352271,
    "y":-71.05524200000001
  },
  {
    "Line":"Red",
    "Stop":"Wollaston",
    "x":42.2665139,
    "y":-71.0203369
  }
]